setup.py
EsosaAI_probability/Binomialdistribution.py
EsosaAI_probability/Gaussiandistribution.py
EsosaAI_probability/Generaldistribution.py
EsosaAI_probability/__init__.py
EsosaAI_probability.egg-info/PKG-INFO
EsosaAI_probability.egg-info/SOURCES.txt
EsosaAI_probability.egg-info/dependency_links.txt
EsosaAI_probability.egg-info/not-zip-safe
EsosaAI_probability.egg-info/top_level.txt