Metadata-Version: 2.1
Name: EsosaAI-probability
Version: 1.1
Summary: Guassian and Binomial distributions
Author: Esosa Asemota
Author-email: a_esosa@yahoo.com
